{
    "packages": [],
    "includes": {
        "include/all$a00ae8ee5ed761e8dcac11e803acda36ad157759.json": {
            "sha1": "a00ae8ee5ed761e8dcac11e803acda36ad157759"
        }
    },
    "metadata-url": "/pco-bcp/satis/main/repository/p2/%package%.json",
    "available-packages": [
        "pco-bcp/dpm_modules",
        "pco-bcp/dpm_theme",
        "pco-bcp/impact_bootstrap",
        "pco-bcp/pco_cities",
        "pco-bcp/pco_modules",
        "pco-bcp/pm_modules",
        "pco-bcp/pm_theme",
        "pco-bcp/site-pco-impactcanada"
    ]
}
