{
    "packages": [],
    "includes": {
        "include/all$efcffcd8d25b5d2ac19386c9bb511cc0664667db.json": {
            "sha1": "efcffcd8d25b5d2ac19386c9bb511cc0664667db"
        }
    },
    "metadata-url": "/pco-bcp/satis/main/repository/p2/%package%.json",
    "available-packages": [
        "pco-bcp/dpm_modules",
        "pco-bcp/dpm_theme",
        "pco-bcp/impact_bootstrap",
        "pco-bcp/pco_cities",
        "pco-bcp/pco_modules",
        "pco-bcp/pm_modules",
        "pco-bcp/pm_theme",
        "pco-bcp/site-pco-impactcanada"
    ]
}
