{
    "packages": [],
    "includes": {
        "include/all$1ab3083051e5c32081f5d28ccbffae9d9673ee88.json": {
            "sha1": "1ab3083051e5c32081f5d28ccbffae9d9673ee88"
        }
    },
    "metadata-url": "/pco-bcp/satis/main/repository/p2/%package%.json",
    "available-packages": [
        "pco-bcp/dpm_modules",
        "pco-bcp/dpm_theme",
        "pco-bcp/impact_bootstrap",
        "pco-bcp/pco_cities",
        "pco-bcp/pco_modules",
        "pco-bcp/pm_modules",
        "pco-bcp/pm_theme",
        "pco-bcp/site-pco-impactcanada"
    ]
}
