{
    "packages": [],
    "includes": {
        "include/all$d56b4ee91b490af89d358b3a6b9c89109a0eb091.json": {
            "sha1": "d56b4ee91b490af89d358b3a6b9c89109a0eb091"
        }
    },
    "metadata-url": "/pco-bcp/satis/main/repository/p2/%package%.json",
    "available-packages": [
        "pco-bcp/dpm_modules",
        "pco-bcp/dpm_theme",
        "pco-bcp/impact_bootstrap",
        "pco-bcp/pco_cities",
        "pco-bcp/pco_modules",
        "pco-bcp/pm_modules",
        "pco-bcp/pm_theme",
        "pco-bcp/site-pco-impactcanada"
    ]
}
