{
    "packages": [],
    "includes": {
        "include/all$c5eb9cf25cfb53a360ffe9fc4edd928bbcf2ef88.json": {
            "sha1": "c5eb9cf25cfb53a360ffe9fc4edd928bbcf2ef88"
        }
    },
    "metadata-url": "/pco-bcp/satis/main/repository/p2/%package%.json",
    "available-packages": [
        "pco-bcp/dpm_modules",
        "pco-bcp/dpm_theme",
        "pco-bcp/impact_bootstrap",
        "pco-bcp/pco_cities",
        "pco-bcp/pco_modules",
        "pco-bcp/pm_modules",
        "pco-bcp/pm_theme",
        "pco-bcp/site-pco-impactcanada"
    ]
}
