{
    "packages": [],
    "includes": {
        "include/all$670b996ee36548aa14d1f1c2797ad2f8ddfa9d4f.json": {
            "sha1": "670b996ee36548aa14d1f1c2797ad2f8ddfa9d4f"
        }
    },
    "metadata-url": "/pco-bcp/satis/main/repository/p2/%package%.json",
    "available-packages": [
        "pco-bcp/dpm_modules",
        "pco-bcp/dpm_theme",
        "pco-bcp/impact_bootstrap",
        "pco-bcp/pco_cities",
        "pco-bcp/pco_modules",
        "pco-bcp/pm_modules",
        "pco-bcp/pm_theme",
        "pco-bcp/site-pco-impactcanada"
    ]
}
