{
    "packages": [],
    "includes": {
        "include/all$37f7c4cfd724201a65ab2f58f380fa33f400799a.json": {
            "sha1": "37f7c4cfd724201a65ab2f58f380fa33f400799a"
        }
    },
    "metadata-url": "/pco-bcp/satis/main/repository/p2/%package%.json",
    "available-packages": [
        "pco-bcp/dpm_modules",
        "pco-bcp/dpm_theme",
        "pco-bcp/impact_bootstrap",
        "pco-bcp/pco_cities",
        "pco-bcp/pco_modules",
        "pco-bcp/pm_modules",
        "pco-bcp/pm_theme",
        "pco-bcp/site-pco-impactcanada"
    ]
}
