{
    "packages": [],
    "includes": {
        "include/all$877f067573b3b07da6aee69c479da68001ee87dc.json": {
            "sha1": "877f067573b3b07da6aee69c479da68001ee87dc"
        }
    },
    "metadata-url": "/pco-bcp/satis/main/repository/p2/%package%.json",
    "available-packages": [
        "pco-bcp/dpm_modules",
        "pco-bcp/dpm_theme",
        "pco-bcp/impact_bootstrap",
        "pco-bcp/pco_cities",
        "pco-bcp/pco_modules",
        "pco-bcp/pm_modules",
        "pco-bcp/pm_theme",
        "pco-bcp/site-pco-impactcanada"
    ]
}
