{
    "packages": [],
    "includes": {
        "include/all$65a99d535ad2d1d124b06043d0b242c4470c8f14.json": {
            "sha1": "65a99d535ad2d1d124b06043d0b242c4470c8f14"
        }
    },
    "metadata-url": "/pco-bcp/satis/main/repository/p2/%package%.json",
    "available-packages": [
        "pco-bcp/dpm_modules",
        "pco-bcp/dpm_theme",
        "pco-bcp/impact_bootstrap",
        "pco-bcp/pco_cities",
        "pco-bcp/pco_modules",
        "pco-bcp/pm_modules",
        "pco-bcp/pm_theme",
        "pco-bcp/site-pco-impactcanada"
    ]
}
