{
    "packages": [],
    "includes": {
        "include/all$98bc8a161f39641cc92f29ead86a02cfa48741c4.json": {
            "sha1": "98bc8a161f39641cc92f29ead86a02cfa48741c4"
        }
    },
    "metadata-url": "/pco-bcp/satis/main/repository/p2/%package%.json",
    "available-packages": [
        "pco-bcp/dpm_modules",
        "pco-bcp/dpm_theme",
        "pco-bcp/impact_bootstrap",
        "pco-bcp/pco_cities",
        "pco-bcp/pco_modules",
        "pco-bcp/pm_modules",
        "pco-bcp/pm_theme",
        "pco-bcp/site-pco-impactcanada"
    ]
}
