{
    "packages": [],
    "includes": {
        "include/all$f3e203426a1f4186b55f5f4f80defd8ad3ac9c13.json": {
            "sha1": "f3e203426a1f4186b55f5f4f80defd8ad3ac9c13"
        }
    },
    "metadata-url": "/pco-bcp/satis/main/repository/p2/%package%.json",
    "available-packages": [
        "pco-bcp/dpm_modules",
        "pco-bcp/dpm_theme",
        "pco-bcp/impact_bootstrap",
        "pco-bcp/pco_cities",
        "pco-bcp/pco_modules",
        "pco-bcp/pm_modules",
        "pco-bcp/pm_theme",
        "pco-bcp/site-pco-impactcanada"
    ]
}
