{
    "packages": [],
    "includes": {
        "include/all$a45da3d57d180726116f60ea31430bc1e6d17e74.json": {
            "sha1": "a45da3d57d180726116f60ea31430bc1e6d17e74"
        }
    },
    "metadata-url": "/pco-bcp/satis/main/repository/p2/%package%.json",
    "available-packages": [
        "pco-bcp/dpm_modules",
        "pco-bcp/dpm_theme",
        "pco-bcp/impact_bootstrap",
        "pco-bcp/pco_cities",
        "pco-bcp/pco_modules",
        "pco-bcp/pm_modules",
        "pco-bcp/pm_theme",
        "pco-bcp/site-pco-impactcanada"
    ]
}
