{
    "packages": [],
    "includes": {
        "include/all$bd58ec279e41c209233a4bf42f2c4517d010bced.json": {
            "sha1": "bd58ec279e41c209233a4bf42f2c4517d010bced"
        }
    },
    "metadata-url": "/pco-bcp/satis/main/repository/p2/%package%.json",
    "available-packages": [
        "pco-bcp/dpm_modules",
        "pco-bcp/dpm_theme",
        "pco-bcp/impact_bootstrap",
        "pco-bcp/pco_cities",
        "pco-bcp/pco_modules",
        "pco-bcp/pm_modules",
        "pco-bcp/pm_theme",
        "pco-bcp/site-pco-impactcanada"
    ]
}
