{
    "packages": [],
    "includes": {
        "include/all$490cec593947c8b903d3bea738b603ab18cda3a3.json": {
            "sha1": "490cec593947c8b903d3bea738b603ab18cda3a3"
        }
    },
    "metadata-url": "/pco-bcp/satis/main/repository/p2/%package%.json",
    "available-packages": [
        "pco-bcp/dpm_modules",
        "pco-bcp/dpm_theme",
        "pco-bcp/impact_bootstrap",
        "pco-bcp/pco_cities",
        "pco-bcp/pco_modules",
        "pco-bcp/pm_modules",
        "pco-bcp/pm_theme",
        "pco-bcp/site-pco-impactcanada"
    ]
}
