{
    "packages": [],
    "includes": {
        "include/all$5cc5eb77458497d8e3943b355f27b5c00c07f1a9.json": {
            "sha1": "5cc5eb77458497d8e3943b355f27b5c00c07f1a9"
        }
    },
    "metadata-url": "/pco-bcp/satis/main/repository/p2/%package%.json",
    "available-packages": [
        "pco-bcp/dpm_modules",
        "pco-bcp/dpm_theme",
        "pco-bcp/impact_bootstrap",
        "pco-bcp/pco_cities",
        "pco-bcp/pco_modules",
        "pco-bcp/pm_modules",
        "pco-bcp/pm_theme",
        "pco-bcp/site-pco-impactcanada"
    ]
}
